{"web":{"client_id":"916932200710-197d3s4oroak5c7cmm3cmkoakfahp62e.apps.googleusercontent.com","auth_uri":"https://accounts.google.com/o/oauth2/auth","token_uri":"https://accounts.google.com/o/oauth2/token","auth_provider_x509_cert_url":"https://www.googleapis.com/oauth2/v1/certs","client_email":"","client_x509_cert_url":"","client_secret":"QGxESqAS6qDoCH1lCIqlkJnE","redirect_uris":["http://www.sowntogrow.com/oauth2callback","http://localhost:3000/auth/google_oauth2/callback"],"javascript_origins":["http://www.sowntogrow.com","http://localhost:3000"]}}